smartone/__init__.py
smartone-0.1.0.dist-info/LICENSE
smartone-0.1.0.dist-info/METADATA
smartone-0.1.0.dist-info/WHEEL
smartone-0.1.0.dist-info/RECORD
